moduleOne.py
moduleTwo.py
functionstestasap-0.0.2.dist-info/METADATA
functionstestasap-0.0.2.dist-info/WHEEL
functionstestasap-0.0.2.dist-info/top_level.txt
functionstestasap-0.0.2.dist-info/RECORD
