Metadata-Version: 2.1
Name: functionstestasap
Version: 0.0.2
Summary: Quicksample Test Package for SQLShack Demo
Author: TestNew
Classifier: Programming Language :: Python :: 3
Classifier: License :: OSI Approved :: MIT License
Classifier: Operating System :: OS Independent
Requires-Python: >=3.6
Requires-Dist: datetime
Requires-Dist: openpyxl
Requires-Dist: xlrd
